swarmauri_tool_jupytergetiopubmessage/JupyterGetIOPubMessageTool.py
swarmauri_tool_jupytergetiopubmessage/__init__.py
swarmauri_tool_jupytergetiopubmessage-0.7.5.dist-info/LICENSE
swarmauri_tool_jupytergetiopubmessage-0.7.5.dist-info/METADATA
swarmauri_tool_jupytergetiopubmessage-0.7.5.dist-info/WHEEL
swarmauri_tool_jupytergetiopubmessage-0.7.5.dist-info/entry_points.txt
swarmauri_tool_jupytergetiopubmessage-0.7.5.dist-info/RECORD
