Metadata-Version: 2.3
Name: swarmauri_tool_jupytergetiopubmessage
Version: 0.7.5
Summary: A tool designed to retrieve messages from the IOPub channel of a Jupyter kernel using jupyter_client, capturing cell outputs and logs.
License: Apache-2.0
Author: Jacob Stewart
Author-email: jacob@swarmauri.com
Requires-Python: >=3.10,<3.13
Classifier: License :: OSI Approved :: Apache Software License
Classifier: Programming Language :: Python :: 3.10
Classifier: Programming Language :: Python :: 3.11
Classifier: Programming Language :: Python :: 3.12
Classifier: Programming Language :: Python :: 3.13
Requires-Dist: jupyter_client (>=8.6.3)
Requires-Dist: swarmauri_base
Requires-Dist: swarmauri_core
Requires-Dist: swarmauri_standard
Requires-Dist: websocket-client (>=1.8.0)
